CHANGELOG.md
MANIFEST.in
README.md
RELEASE_CHECK_LIST.md
setup.cfg
setup.py
tests.sh
cmake/qpropgen.cmake
examples/CMakeLists.txt
examples/basesound.yaml
examples/defaults.yaml
examples/example.cpp
examples/impl.yaml
examples/includes.yaml
examples/mutability.yaml
examples/usebaseclass.yaml
qpropgen/__init__.py
qpropgen/fromsrc.py
qpropgen/main.py
qpropgen.egg-info/PKG-INFO
qpropgen.egg-info/SOURCES.txt
qpropgen.egg-info/dependency_links.txt
qpropgen.egg-info/entry_points.txt
qpropgen.egg-info/not-zip-safe
qpropgen.egg-info/requires.txt
qpropgen.egg-info/top_level.txt
qpropgen/templates/template.cpp
qpropgen/templates/template.h