Metadata-Version: 2.1
Name: qpropgen
Version: 0.1.1
Summary: Generate QML-friendly QObject-based C++ classes from class definition files
Home-page: https://github.com/agateau/qpropgen
Author: Aurélien Gâteau
Author-email: mail@agateau.com
License: Apache 2.0
Keywords: qt,qml,commandline,qobject,generator
Platform: any
Classifier: Development Status :: 4 - Beta
Classifier: Environment :: Console
Classifier: Intended Audience :: Developers
Classifier: License :: OSI Approved :: Apache Software License
Classifier: Programming Language :: Python :: 3
Classifier: Topic :: Software Development :: Build Tools
